release_me/__init__.py
release_me/cli.py
release_me/client.py
release_me-0.3.1.dist-info/DESCRIPTION.rst
release_me-0.3.1.dist-info/METADATA
release_me-0.3.1.dist-info/RECORD
release_me-0.3.1.dist-info/WHEEL
release_me-0.3.1.dist-info/entry_points.txt
release_me-0.3.1.dist-info/metadata.json
release_me-0.3.1.dist-info/pbr.json
release_me-0.3.1.dist-info/top_level.txt
